LICENSE
MANIFEST.in
setup.py
tree/__init__.py
tree/admin.py
tree/conf.py
tree/menu.py
tree/models.py
tree/urls.py
tree/utility.py
tree/views.py
tree/middleware/__init__.py
tree/middleware/upy_context.py
tree/static/tree/css/page_info.css
tree/static/tree/images/default-bg.gif
tree/static/tree/images/favicon.ico
tree/static/tree/images/help.gif
tree/static/tree/images/important.gif
tree/static/tree/images/info.gif
tree/static/tree/images/item_editor_form_title.png
tree/static/tree/images/magnifier.png
tree/static/tree/images/nav-bg.gif
tree/static/tree/images/title.gif
tree/static/tree/images/toggle-collapse-dark.png
tree/static/tree/images/toggle-expand-dark.png
tree/static/tree/images/wrench.png
tree/static/tree/js/template.js
tree/static/tree/js/treenode.js
tree/static/tree/js/view.js
tree/template_context/__init__.py
tree/template_context/context_processors.py
tree/templates/page_info.html
tree/templates/tree_base.html
tree/templates/tpl/breadcrumb_as_p.tpl.html
tree/templates/tpl/breadcrumb_as_p.tpl.source.html
tree/templates/tpl/breadcrumb_as_string.tpl.html
tree/templates/tpl/breadcrumb_as_string.tpl.source.html
tree/templates/tpl/breadcrumb_as_ul.tpl.html
tree/templates/tpl/breadcrumb_as_ul.tpl.source.html
tree/templates/tpl/menu_as_p.tpl.html
tree/templates/tpl/menu_as_p.tpl.source.html
tree/templates/tpl/menu_as_string.tpl.html
tree/templates/tpl/menu_as_string.tpl.source.html
tree/templates/tpl/menu_as_ul.tpl.html
tree/templates/tpl/menu_as_ul.tpl.source.html
tree/templates/tpl/robots.tpl.html
tree/templates/tpl/sitemap.tpl.html
twentytab_tree.egg-info/PKG-INFO
twentytab_tree.egg-info/SOURCES.txt
twentytab_tree.egg-info/dependency_links.txt
twentytab_tree.egg-info/requires.txt
twentytab_tree.egg-info/top_level.txt