Metadata-Version: 1.0
Name: twentytab-tree
Version: 0.7
Summary: A django app that allows to create a tree menu and breadcrumb. It provides to create also urls, views and template.
Home-page: https://github.com/20tab/twentytab-tree
Author: 20tab S.r.l.
Author-email: info@20tab.com
License: MIT License
Platform: UNKNOWN
